cgshop2020_pyutils/__init__.py
cgshop2020_pyutils/checker.py
cgshop2020_pyutils/clib.py
cgshop2020_pyutils/instance.py
cgshop2020_pyutils/instance_base_database.py
cgshop2020_pyutils/instance_database.py
cgshop2020_pyutils/instance_file_database.py
cgshop2020_pyutils/instance_reader.py
cgshop2020_pyutils/instance_zip_database.py
cgshop2020_pyutils/solution.py
cgshop2020_pyutils/solution_reader.py
cgshop2020_pyutils/solution_set.py
cgshop2020_pyutils/solution_writer.py
cgshop2020_pyutils/trivial_triangulation_solver.py
cgshop2020_pyutils/visualizer.py
cgshop2020_pyutils/zip_reader.py
cgshop2020_pyutils/zip_reader_errors.py
cgshop2020_pyutils/zip_writer.py
cgshop2020_pyutils/cpp_core/CMakeLists.txt
cgshop2020_pyutils/cpp_core/binaries/linux-x86_64/libcgshop2020_trivial_triangulation_solver_module.so
cgshop2020_pyutils/cpp_core/binaries/linux-x86_64/libcgshop2020_verifier_module.so
cgshop2020_pyutils/cpp_core/binaries/linux-x86_64/with-debinfo/libcgshop2020_trivial_triangulation_solver_module.so
cgshop2020_pyutils/cpp_core/binaries/linux-x86_64/with-debinfo/libcgshop2020_verifier_module.so
cgshop2020_pyutils/cpp_core/binaries/osx/libcgshop2020_trivial_triangulation_solver_module.so
cgshop2020_pyutils/cpp_core/binaries/osx/libcgshop2020_verifier_module.so
cgshop2020_pyutils/cpp_core/binaries/osx/with-debinfo/libcgshop2020_trivial_triangulation_solver_module.so
cgshop2020_pyutils/cpp_core/binaries/osx/with-debinfo/libcgshop2020_verifier_module.so
cgshop2020_pyutils/cpp_core/binaries/win64/CGAL-vc140-mt-4.14.dll
cgshop2020_pyutils/cpp_core/binaries/win64/CGAL_Core-vc140-mt-4.14.dll
cgshop2020_pyutils/cpp_core/binaries/win64/api-ms-win-core-console-l1-1-0.dll
cgshop2020_pyutils/cpp_core/binaries/win64/api-ms-win-core-datetime-l1-1-0.dll
cgshop2020_pyutils/cpp_core/binaries/win64/api-ms-win-core-debug-l1-1-0.dll
cgshop2020_pyutils/cpp_core/binaries/win64/api-ms-win-core-errorhandling-l1-1-0.dll
cgshop2020_pyutils/cpp_core/binaries/win64/api-ms-win-core-file-l1-1-0.dll
cgshop2020_pyutils-0.4.4.dist-info/LICENSE
cgshop2020_pyutils-0.4.4.dist-info/METADATA
cgshop2020_pyutils-0.4.4.dist-info/WHEEL
cgshop2020_pyutils-0.4.4.dist-info/top_level.txt
cgshop2020_pyutils-0.4.4.dist-info/RECORD
