Metadata-Version: 2.1
Name: cgshop2020-pyutils
Version: 0.4.4
Summary: Utilities for the CG:SHOP 2020 Optimization Competition on the Minimum Convex Partition Problem.
Home-page: https://cgshop.ibr.cs.tu-bs.de/competition/cg-shop-2020/
Author: TU Braunschweig, IBR, Algorithms Group (Phillip Keldenich and Dominik Krupke)
Author-email: keldenich@ibr.cs.tu-bs.de, krupke@ibr.cs.tu-bs.de
License: UNKNOWN
Platform: UNKNOWN
Classifier: Programming Language :: Python :: 3
Classifier: Programming Language :: C++
Classifier: License :: OSI Approved :: MIT License
Classifier: Development Status :: 4 - Beta
Requires-Python: >=3.6
Requires-Dist: matplotlib
Requires-Dist: chardet
